hpc_launcher/__init__.py
hpc_launcher/utils.py
hpc_launcher/version.py
hpc_launcher/cli/__init__.py
hpc_launcher/cli/common_args.py
hpc_launcher/cli/console_pipe.py
hpc_launcher/cli/launch.py
hpc_launcher/cli/launch_helpers.py
hpc_launcher/cli/torchrun_hpc.py
hpc_launcher/schedulers/__init__.py
hpc_launcher/schedulers/flux.py
hpc_launcher/schedulers/local.py
hpc_launcher/schedulers/lsf.py
hpc_launcher/schedulers/scheduler.py
hpc_launcher/schedulers/slurm.py
hpc_launcher/systems/__init__.py
hpc_launcher/systems/autodetect.py
hpc_launcher/systems/configure.py
hpc_launcher/systems/system.py
hpc_launcher/systems/lc/__init__.py
hpc_launcher/systems/lc/cts2.py
hpc_launcher/systems/lc/el_capitan_family.py
hpc_launcher/systems/lc/sierra_family.py
hpc_launcher/torch/__init__.py
hpc_launcher/torch/torchrun_hpc_trampoline.py
hpc_launcher-1.0.4.dist-info/licenses/LICENSE
hpc_launcher-1.0.4.dist-info/METADATA
hpc_launcher-1.0.4.dist-info/WHEEL
hpc_launcher-1.0.4.dist-info/entry_points.txt
hpc_launcher-1.0.4.dist-info/top_level.txt
hpc_launcher-1.0.4.dist-info/RECORD
