Metadata-Version: 2.4
Name: hpc-launcher
Version: 1.0.4
Summary: LBANN Launcher utilities for distributed jobs on HPC clusters
Home-page: https://github.com/LBANN/HPC-launcher
Author: Lawrence Livermore National Laboratory
Author-email: lbann@llnl.gov
License: Apache-2.0
Classifier: Programming Language :: Python :: 3
Classifier: Operating System :: OS Independent
Requires-Python: >=3.9
License-File: LICENSE
Requires-Dist: psutil
Requires-Dist: nvidia-ml-py
Provides-Extra: torch
Requires-Dist: torch; extra == "torch"
Requires-Dist: numpy; extra == "torch"
Provides-Extra: mpi
Requires-Dist: mpi4py>=3.1.4; extra == "mpi"
Requires-Dist: mpi_rdv; extra == "mpi"
Provides-Extra: testing
Requires-Dist: pytest; extra == "testing"
Provides-Extra: e2e-testing
Requires-Dist: accelerate; extra == "e2e-testing"
Dynamic: author
Dynamic: author-email
Dynamic: classifier
Dynamic: description
Dynamic: description-content-type
Dynamic: home-page
Dynamic: license
Dynamic: license-file
Dynamic: provides-extra
Dynamic: requires-dist
Dynamic: requires-python
Dynamic: summary
